{
  "id": "2423838",
  "name": "demo",
  "font_family": "iconfont",
  "css_prefix_text": "icon",
  "description": "",
  "glyphs": [
    {
      "icon_id": "9004636",
      "name": "radio",
      "font_class": "radio",
      "unicode": "e61a",
      "unicode_decimal": 58906
    },
    {
      "icon_id": "9752478",
      "name": "radio",
      "font_class": "radio1",
      "unicode": "e604",
      "unicode_decimal": 58884
    },
    {
      "icon_id": "21170989",
      "name": "未选中",
      "font_class": "weixuanzhong",
      "unicode": "e618",
      "unicode_decimal": 58904
    },
    {
      "icon_id": "21170990",
      "name": "选中",
      "font_class": "xuanzhong",
      "unicode": "e619",
      "unicode_decimal": 58905
    },
    {
      "icon_id": "20776273",
      "name": "警告",
      "font_class": "jinggao",
      "unicode": "e617",
      "unicode_decimal": 58903
    },
    {
      "icon_id": "20775545",
      "name": "单元",
      "font_class": "danyuan",
      "unicode": "e616",
      "unicode_decimal": 58902
    },
    {
      "icon_id": "20435137",
      "name": "返回",
      "font_class": "fanhui",
      "unicode": "e605",
      "unicode_decimal": 58885
    },
    {
      "icon_id": "20435138",
      "name": "关闭",
      "font_class": "guanbi",
      "unicode": "e606",
      "unicode_decimal": 58886
    },
    {
      "icon_id": "20435139",
      "name": "加入",
      "font_class": "jiaru",
      "unicode": "e607",
      "unicode_decimal": 58887
    },
    {
      "icon_id": "20435140",
      "name": "箭头",
      "font_class": "jiantou",
      "unicode": "e608",
      "unicode_decimal": 58888
    },
    {
      "icon_id": "20435141",
      "name": "创建",
      "font_class": "chuangjian",
      "unicode": "e609",
      "unicode_decimal": 58889
    },
    {
      "icon_id": "20435142",
      "name": "输入密码",
      "font_class": "shurumima",
      "unicode": "e60a",
      "unicode_decimal": 58890
    },
    {
      "icon_id": "20435143",
      "name": "设置",
      "font_class": "shezhi",
      "unicode": "e60b",
      "unicode_decimal": 58891
    },
    {
      "icon_id": "20435144",
      "name": "保存图片",
      "font_class": "baocuntupian",
      "unicode": "e60c",
      "unicode_decimal": 58892
    },
    {
      "icon_id": "20435145",
      "name": "我的",
      "font_class": "wode",
      "unicode": "e60d",
      "unicode_decimal": 58893
    },
    {
      "icon_id": "20435146",
      "name": "选择日期",
      "font_class": "xuanzeriqi",
      "unicode": "e60e",
      "unicode_decimal": 58894
    },
    {
      "icon_id": "20435147",
      "name": "选择时间",
      "font_class": "xuanzeshijian",
      "unicode": "e60f",
      "unicode_decimal": 58895
    },
    {
      "icon_id": "20435148",
      "name": "右滑",
      "font_class": "youhua",
      "unicode": "e610",
      "unicode_decimal": 58896
    },
    {
      "icon_id": "20435149",
      "name": "生成海报",
      "font_class": "shengchenghaibao",
      "unicode": "e611",
      "unicode_decimal": 58897
    },
    {
      "icon_id": "20435150",
      "name": "微信",
      "font_class": "weixin",
      "unicode": "e612",
      "unicode_decimal": 58898
    },
    {
      "icon_id": "20435151",
      "name": "形状",
      "font_class": "xingzhuang",
      "unicode": "e613",
      "unicode_decimal": 58899
    },
    {
      "icon_id": "20435152",
      "name": "左滑",
      "font_class": "zuohua",
      "unicode": "e614",
      "unicode_decimal": 58900
    },
    {
      "icon_id": "20435153",
      "name": "关于我们",
      "font_class": "guanyuwomen",
      "unicode": "e615",
      "unicode_decimal": 58901
    }
  ]
}
